{
  "clubsData": [
     {
      "id": 1,
      "name": "DENVER GAME CLUB",
      "description": "4 кабинки 5x5 + Вип & Люкс кабинки. Переферия от Redragon и HyperX",
      "location": {
        "address": "\u200BЧиланзар Ц квартал микрорайон, 1а/1\u200B1 этаж",
        "coordinates": [41.315569, 69.279737],
        "time": "Круглосуточно"
      },
      "photos": ["https://lh3.googleusercontent.com/p/AF1QipMa8c9hEFJkd7tR6CXnOP79BLgSuVpOBgJYwuh-=s1360-w1360-h1020-rw",
                 "https://i4.photo.2gis.com/images/branch/0/30258560163944869_b67b_328x170.jpg"],

      "reviews": [
        {
          "user": "Ulugbek Khudoynazarov",
          "rating": 5,
          "text": "Очень крутое место! Мощные компы, уютная атмосфера, бар с хот-догами и многими другими снеками. Приходите не пожалеете!"
        }
      ],
      "administration": {
        "contact": "-",
        "number": "+998 99‒022‒68‒68, +998 99‒023‒68‒68"
      },
      "services": {
        "Wi-Fi": true,
        "bar": true,
        "kitchen": true,
        "consoles": true,
        "games": true,
        "relaxation_zones": true
      },
      "prices": {
        "pc_rent_STANDART": 14400,
      "pc_rent_VIP": 17700,
        "special_offers": "Скидка 20% после 22:00"
      },
      "working_hours": "9:00 - 24:00",
      "club_card": {
        "loyalty_program": true,
        "benefits": "Скидки постоянным клиентам, бонусные игры"
      },
      "comments": "Дополнительная информация и акции доступны на сайте клуба"
    },
     {
      "id": 2,
      "name": "Bazz Game",
      "description": "\uD83C\uDFAE✨ Привет, друзья! Представляем настоящий рай для геймеров - BAZZ cyber lounge! \uD83C\uDF89\uD83D\uDD79✨",
      "location": {
        "address": "Осиё улица, 23\u200B1 этаж\nЮнусабадский район, Ташкент",
        "coordinates": [41.327438, 69.288208],
        "time": "Круглосуточно"
      },
      "photos": [
        "https://ams2-cdn.2gis.com/previews/1186336940887113731/b0988d0a-8205-47dc-898e-ea04c92666b9/3/ru/328x170?api-version=2.0",
        "https://i1.photo.2gis.com/images/branch/0/30258560169454547_f423_328x170.jpg"],
      "reviews": [
        {
          "user": "АЛЯ МАНТЕРА",
          "rating": 5,
          "text": "Крутой клуб мне зашел он"
        }
      ],
      "administration": {
        "contact": "info@cluba.com",
        "number": "+998 (77) 704‒03‒33"
      },
       "services": {
        "Wi-Fi": true,
        "bar": true,
        "kitchen": true,
        "consoles": true,
        "games": true,
        "relaxation_zones": true
      },
      "prices": {
        "pc_rent_STANDART": 17000,
      "pc_rent_VIP": 20000,
        "special_offers": "Скидка 20% после 22:00"
      },
      "working_hours": "24/7",
      "club_card": {
        "loyalty_program": true,
        "benefits": "Скидки постоянным клиентам, бонусные игры"
      },
      "comments": "Дополнительная информация и акции доступны на сайте клуба"
    },
        {
          "id": 3,
      "name": "Invictus Gaming Club",
      "description": "Здесь в свободной уличной атмосфере с граффити на стенах и с самой лучшей игровой гарнитурой , вы можете не просто поиграть в Dota и CS:GO.",
      "location": {
        "address": "\u200BФидокор, 32а\u200Bцокольный этаж\u200B2 филиала\nЛолазор ж/м, Мирабадский район, Ташкент",
        "coordinates": [41.324987, 69.290505],
        "time": "Круглосуточно"
      },
      "photos": [
        "https://i9.photo.2gis.com/images/branch/0/30258560095057456_9600_328x170.jpg",
        "https://i5.photo.2gis.com/images/branch/0/30258560095057463_506d_328x170.jpg"
      ],
      "reviews": [
        {
          "user": "\u200BErnazar Tajimuratov",
          "rating": 5,
          "text": "Нам нравитя советую как постоянные клиенты"
        }
      ],
      "administration": {
        "contact": "mvp.2gis.biz",
        "number": "+998 90‒017‒14‒00"
      },
       "services": {
        "Wi-Fi": true,
        "bar": true,
        "kitchen": true,
        "consoles": true,
        "games": true,
        "relaxation_zones": true
      },
      "prices": {
        "pc_rent_STANDART": 15000,
      "pc_rent_VIP": 25000,
        "special_offers": "Скидка 20% после 22:00"
      },
      "working_hours": "24/7",
      "club_card": {
        "loyalty_program": true,
        "benefits": "Скидки постоянным клиентам, бонусные игры"
      },
      "comments": "Дополнительная информация и акции доступны на сайте клуба"
    },
            {
      "id": 4,
      "name": "Colizeum",
      "description": "COLIZEUM — это максимальное удовольствие от игры.",
      "location": {
        "address": "\u200BБЦ Gc\u200BНиёзбек Йули, 30\u200B-1 этаж\nМирзо-Улугбекский район, Ташкент",
        "coordinates": [41.324987, 69.290505],
        "time": "Круглосуточно"
      },
      "photos": [
        "https://i9.photo.2gis.com/images/branch/0/30258560095057456_9600_328x170.jpg",
        "https://i5.photo.2gis.com/images/branch/0/30258560095057463_506d_328x170.jpg"

      ],
      "reviews": [
        {
          "user": "\u200BЕвгений Измайлов",
          "rating": 5,
          "text": "Отличный компьютерный клуб, приехали к друзьям на недельку, решили зайти сюда и не прогадали. Отличные сотрудники, классное железо и интерьер. Будем приходить ещё"
        }
      ],
      "administration": {
        "contact": "colizeum.toshkent@gmail.com",
        "number": "+998 90‒017‒14‒00"
      },
      "services": {
        "Wi-Fi": true,
        "bar":   true,
        "kitchen": true,
        "consoles": true,
        "games": true,
        "relaxation_zones": true
      },
      "prices": {
        "pc_rent_STANDART": 17000,
      "pc_rent_VIP": 24000,
        "special_offers": "Скидка 20% после 22:00"
      },
      "working_hours": "24/7",
      "club_card": {
        "loyalty_program": true,
        "benefits": "Скидки постоянным клиентам, бонусные игры"
      },
      "comments": "Дополнительная информация и акции доступны на сайте клуба"
    },
                {
      "id": 5,
      "name": "MAJOR Premium Gaming",
      "description": "Major Premium Gaming — киберспортивный проект,объединивший ценителей компьютерных видеоигр,игроков и фанатов.",
      "location": {
        "address": "\u200BЖилмассив Кораташ, 32а\u200Bцокольный этаж\u200B4 филиала\nКараташ ж/м, Шайхантахурский район, Ташкент, 100021",
        "coordinates": [41.298058, 69.280117],
        "time": "Круглосуточно"
      },
      "photos": [
        "https://i6.photo.2gis.com/images/branch/0/30258560075645251_1643_328x170.jpg",
        "https://i1.photo.2gis.com/images/branch/0/30258560075645252_562c_328x170.jpg"

      ],
      "reviews": [
        {
          "user": "\u200BЕвгений Измайлов",
          "rating": 5,
          "text": "Отличный компьютерный клуб, приехали к друзьям на недельку, решили зайти сюда и не прогадали. Отличные сотрудники, классное железо и интерьер. Будем приходить ещё"
        }
      ],
      "administration": {
        "contact": "majorclub.uz@gmail.com",
        "number": "+998 (78) 888‒15‒55"
      },
      "services": {
        "Wi-Fi": true,
        "bar":   true,
        "kitchen": true,
        "consoles": true,
        "games": true,
        "relaxation_zones": true
      },
      "prices": {
        "pc_rent_STANDART": 8000,
      "pc_rent_VIP": 10000,
        "special_offers": "Скидка 20% после 22:00"
      },
      "working_hours": "24/7",
      "club_card": {
        "loyalty_program": true,
        "benefits": "Скидки постоянным клиентам, бонусные игры"
      },
      "comments": "Дополнительная информация и акции доступны на сайте клуба"
    },
        {
      "id": 6,
      "name": "MVP Gaming Club",
      "description": "• МВП - компьютерный клуб формата кибер лаунж основой которого является стилистика киберпанка.",
      "location": {
        "address": "\u200BМинор жилмассив, 57\u200Bцокольный этаж\u200B3 филиала\nМинор (Ц-6) ж/м, Юнусабадский район, Ташкент",
        "coordinates": [41.331208, 69.281809],
        "time": "Круглосуточно"
      },
      "photos": [
        "https://ams2-cdn.2gis.com/previews/1168500954606075904/6c02c04f-fd0f-4dc0-a187-f5f149a948d5/3/ru/328x170?api-version=2.0",
        "https://i7.photo.2gis.com/images/branch/0/30258560107311803_2e0e_328x170.jpg"

      ],
      "reviews": [
        {
          "user": "\n\u200BRustam Sobirov",
          "rating": 5,
          "text": "Не плохой компьютерный клуб. Недорого!"
        }
      ],
      "administration": {
        "contact": "mvpuzbekistan@gmail.com",
        "number": "+998 95‒777‒77‒73, +998 95‒078‒77‒73"
      },
      "services": {
        "Wi-Fi": true,
        "bar":   true,
        "kitchen": true,
        "consoles": true,
        "games": true,
        "relaxation_zones": true
      },
      "prices": {
        "pc_rent_STANDART": 20000,
      "pc_rent_VIP": 50000,
        "special_offers": "Скидка 20% после 22:00"
      },
      "working_hours": "24/7",
      "club_card": {
        "loyalty_program": true,
        "benefits": "Скидки постоянным клиентам, бонусные игры"
      },
      "comments": "Дополнительная информация и акции доступны на сайте клуба"
    },
            {
      "id": 7,
      "name": "Arcada",
      "description": "Мощные компьютеры и профессиональная периферия, удобные кресла.\nУ нас часто проводятся турниры, акции и скидки, чтобы быть в курсе следи за на нами в Instagram.",
      "location": {
        "address": "\u200BКушбеги микрорайон, 5а\u200Bцокольный этаж\u200B2 филиала\nКушбеги ж/м, Яккасарайский район, Ташкент, 100022",
        "coordinates": [41.268030, 69.244299],
        "time": "Круглосуточно"
      },
      "photos": [
        "https://ams2-cdn.2gis.com/previews/1168500954606075904/6c02c04f-fd0f-4dc0-a187-f5f149a948d5/3/ru/328x170?api-version=2.0",
        "https://i7.photo.2gis.com/images/branch/0/30258560107311803_2e0e_328x170.jpg"

      ],
      "reviews": [
        {
          "user": "\u200BNuradil Yerbolov",
          "rating": 3,
          "text": "3 звезды чисто из-за девайсов -2 потому что не смог поиграть фейсит ("
        }
      ],
      "administration": {
        "contact": "arcadagameclub@gmail.com",
        "number": "+998 (71) 230‒01‒99, +998 90‒906‒88‒33"
      },
      "services": {
        "Wi-Fi": true,
        "bar":   true,
        "kitchen": true,
        "consoles": true,
        "games": true,
        "relaxation_zones": true
      },
      "prices": {
        "pc_rent_STANDART": 14000,
      "pc_rent_VIP": 18000,
        "special_offers": "Скидка 20% после 22:00"
      },
      "working_hours": "24/7",
      "club_card": {
        "loyalty_program": true,
        "benefits": "Скидки постоянным клиентам, бонусные игры"
      },
      "comments": "Дополнительная информация и акции доступны на сайте клуба"
    },
                {
      "id": 8,
      "name": "FPS Gaming",
      "description": "\uD83D\uDDA5Топ 40 мощных компьютеров\n\uD83C\uDFAEВидеокарты RTX 3060 12GB\n\uD83D\uDDB1⌨\uD83C\uDFA7Периферия от HYPERX и DURGOD\n\uD83D\uDDA5Мониторы от MSI 180hz IPS и G-SYNQ",
      "location": {
        "address": "\u200BЭзгулик, 1/1\u200Bцокольный этаж\nЮнусабадский район, Ташкент",
        "coordinates": [41.344725, 69.288578],
        "time": "Ежедневно с 10:00 до 01:00"
      },
      "photos": [
        "https://ams2-cdn.2gis.com/previews/1186258519842619395/557deb83-b754-458d-ae03-aa0ff284ddd9/3/ru/328x170?api-version=2.0",
        "https://i3.photo.2gis.com/images/branch/0/30258560169511427_f3eb_328x170.jpg"

      ],
      "reviews": [
        {
          "user": "Timur Djusipov",
          "rating": 5,
          "text": "\uD83D\uDC4Dместо супер приходите"
        }
      ],
      "administration": {
        "contact": "arcadagameclub@gmail.com",
        "number": "+998 (77) 021‒44‒04"
      },
      "services": {
        "Wi-Fi": true,
        "bar":   true,
        "kitchen": true,
        "consoles": true,
        "games": true,
        "relaxation_zones": true
      },
      "prices": {
        "pc_rent_STANDART": 12000,
      "pc_rent_VIP": 17000,
        "special_offers": "Скидка 20% после 22:00"
      },
      "working_hours": "Ежедневно с 10:00 до 01:00",
      "club_card": {
        "loyalty_program": true,
        "benefits": "Скидки постоянным клиентам, бонусные игры"
      },
      "comments": "Дополнительная информация и акции доступны на сайте клуба"
    },
                    {
      "id": 9,
      "name": "Bulls arena",
      "description": "Круглосуточное место, где можно мериться силами с виртуальными противниками и отлично провести свободное время.",
      "location": {
        "address": "\u200BМассив Ялангач, 30Б\u200Bцокольный этаж\u200B2 филиала\nЯлангач ж/м, Мирзо-Улугбекский район, Ташкент",
        "coordinates": [41.350451, 69.343274],
        "time": "Круглосуточно"
      },
      "photos": [
        "https://wizardpc.net/image/catalog/pcclub/arena-header.jpg",
        "https://encrypted-tbn0.gstatic.com/images?q=tbn:ANd9GcQjAm8fXLU1YbpDUQVwsvH_sHHoj1b1RlkqORzF-lTL-thvG67JnVxkOIHV2lCIuwREDA0&usqp=CAU"

      ],
      "reviews": [
        {
          "user": "ГОЛУБОЙ ЯРУС",
          "rating": 5,
          "text": "\uD83D\uDC4Dместо супер приходите"
        }
      ],
      "administration": {
        "contact": "-",
        "number": "+998 94‒622‒00‒66"
      },
      "services": {
        "Wi-Fi": true,
        "bar":   true,
        "kitchen": true,
        "consoles": true,
        "games": true,
        "relaxation_zones": true
      },
      "prices": {
        "pc_rent_STANDART": 20000,
      "pc_rent_VIP": 26000,
        "special_offers": "Скидка 20% после 22:00"
      },
      "working_hours": "24/7",
      "club_card": {
        "loyalty_program": true,
        "benefits": "Скидки постоянным клиентам, бонусные игры"
      },
      "comments": "Дополнительная информация и акции доступны на сайте клуба"
    },
                        {
      "id": 10,
      "name": "Bezone gaming",
      "description": "Круглосуточное место, где можно мериться силами и членом.",
      "location": {
        "address": "Массив Буюк Ипак Йули, 1\nБуюк Ипак Йули (Ц-1) ж/м, Мирзо-Улугбекский район, Ташкент, 100047",
        "coordinates": [41.313361, 69.287047],
        "time": "Круглосуточно"
      },
      "photos": [
        "https://avatars.mds.yandex.net/get-altay/7044542/2a00000182c6ed18e380dd15b4a27ebf70d9/XXXL",
        "https://avatars.mds.yandex.net/get-altay/7370029/2a00000182c6ecf9fe75bd1d62789a65dae2/XXXL"

      ],
      "reviews": [
        {
          "user": "Zohid Husanov",
          "rating": 5,
          "text": "ВАЩЕ ТОПЧОВОЕ МЕСТА!!!"
        }
      ],
      "administration": {
        "contact": "-",
        "number": "+998 95‒515‒05‒00"
      },
      "services": {
        "Wi-Fi": true,
        "bar":   true,
        "kitchen": true,
        "consoles": true,
        "games": true,
        "relaxation_zones": true
      },
      "prices": {
        "pc_rent_STANDART": 20000,
      "pc_rent_VIP": 28000,
        "special_offers": "Скидка 20% после 22:00"
      },
      "working_hours": "24/7",
      "club_card": {
        "loyalty_program": true,
        "benefits": "Скидки постоянным клиентам, бонусные игры"
      },
      "comments": "Дополнительная информация и акции доступны на сайте клуба"
    },
                            {
      "id": 11,
      "name": "Friends",
      "description": "\uD83C\uDFAE✨ Привет, друзья! Представляем настоящий рай для геймеров - FRIENDS cyber lounge! \uD83C\uDF89\uD83D\uDD79✨",
      "location": {
        "address": "\u200BЖилмассив Себзар, 1\u200Bцокольный этаж\u200B3 филиала\nСебзар (Ц17/18) ж/м, Алмазарский район, Ташкент",
        "coordinates": [41.295912, 69.256408],
        "time": "Круглосуточно"
      },
      "photos": [
        "https://i1.photo.2gis.com/images/branch/0/30258560117939015_c632_328x170.jpg",
        "https://i6.photo.2gis.com/images/geo/0/30258560050754198_add1_328x170.jpg"

      ],
      "reviews": [
        {
          "user": "Камола Мирбабаева",
          "rating": 5,
          "text": "Классное место"
        }
      ],
      "administration": {
        "contact": "-",
        "number": "+998 33‒410‒04‒95"
      },
      "services": {
        "Wi-Fi": true,
        "bar":   true,
        "kitchen": true,
        "consoles": true,
        "games": true,
        "relaxation_zones": true
      },
      "prices": {
        "pc_rent_STANDART": 18000,
      "pc_rent_VIP": 24000,
        "special_offers": "Скидка 20% после 22:00"
      },
      "working_hours": "24/7",
      "club_card": {
        "loyalty_program": true,
        "benefits": "Скидки постоянным клиентам, бонусные игры"
      },
      "comments": "Дополнительная информация и акции доступны на сайте клуба"
    },
                                {
      "id": 12,
      "name": "Dark zone E-sport",
      "description": "\uD83C\uDFAE✨ Привет, друзья! Представляем настоящий рай для геймеров - Dark zone E-sport! \uD83C\uDF89\uD83D\uDD79✨",
      "location": {
        "address": "\u200BУлица Лабзак, 112\u200Bцокольный этаж\u200B6 филиалов\nШайхантахурский район, Ташкент, 100128",
        "coordinates": [41.281905, 69.351811],
        "time": "Круглосуточно"
      },
      "photos": [
        "https://i3.photo.2gis.com/images/branch/0/30258560122840441_9140_328x170.jpg",
        "https://i2.photo.2gis.com/images/branch/0/30258560122840447_758e_328x170.jpg"

      ],
      "reviews": [
        {
          "user": "\u200BАнастасия Чистова",
          "rating": 5,
          "text": "Приехала с подругами, очень крутое место и есть premium кабинка где моники на 360 Ггц что и порадовала \uD83D\uDD25"
        }
      ],
      "administration": {
        "contact": "-",
        "number": "+998 33‒125‒33‒33\nконтакт-центр: круглосуточно\n+998 (77) 777‒43‒24"
      },
      "services": {
        "Wi-Fi": true,
        "bar":   true,
        "kitchen": true,
        "consoles": true,
        "games": true,
        "relaxation_zones": true
      },
      "prices": {
        "pc_rent_STANDART": 15000,
      "pc_rent_VIP": 20000,
        "special_offers": "Скидка 20% после 22:00"
      },
      "working_hours": "24/7",
      "club_card": {
        "loyalty_program": true,
        "benefits": "Скидки постоянным клиентам, бонусные игры"
      },
      "comments": "Дополнительная информация и акции доступны на сайте клуба"
    },
                                    {
      "id": 13,
      "name": "OctaZone",
      "description": "\uD83C\uDFAE✨ Привет, друзья! Представляем настоящий рай для геймеров - Dark zone E-sport! \uD83C\uDF89\uD83D\uDD79✨",
      "location": {
        "address": "\u200BПроспект Амира Темура, 112\u200Bцокольный этаж\nЮнусабадский район, Ташкент, 100099",
        "coordinates": [41.281905, 69.351811],
        "time": "Круглосуточно"
      },
      "photos": [
        "https://encrypted-tbn0.gstatic.com/images?q=tbn:ANd9GcTzVsUDZeCoyWmTlAtJ4yjlfVQXRV2BhNUNBX7uTnTPm1E01Q1JTuLL6EdIr23BSvQYlUc&usqp=CAU",
        "https://encrypted-tbn0.gstatic.com/images?q=tbn:ANd9GcTA_nvbL9ul2dMQVkb2t7MKjPX7Jlfeyg-ZcfgpPg4jsehLilFywCxpPYgJhutrkXGBLWg&usqp=CAU"

      ],
      "reviews": [
        {
          "user": "Kuat Abdurahmanov",
          "rating": 5,
          "text": "Интересный дизайн, хорошие девайсы, удобные кресла, топ железо, своя кухня и нет запахов"
        }
      ],
      "administration": {
        "contact": "-",
        "number": "+998 (55) 520‒22‒02"
      },
      "services": {
        "Wi-Fi": true,
        "bar":   true,
        "kitchen": true,
        "consoles": true,
        "games": true,
        "relaxation_zones": true
      },
      "prices": {
              "pc_rent_STANDART": 16000,
      "pc_rent_VIP": 22000,
        "special_offers": "Скидка 20% после 22:00"
      },
      "working_hours": "24/7",
      "club_card": {
        "loyalty_program": true,
        "benefits": "Скидки постоянным клиентам, бонусные игры"
      },
      "comments": "Дополнительная информация и акции доступны на сайте клуба"
    },
                                        {
      "id": 14,
      "name": "Galakticos",
      "description": "\uD83C\uDFAE✨ Привет, друзья! Представляем настоящий рай для геймеров - GALACTICOS! \uD83C\uDF89\uD83D\uDD79✨",
      "location": {
        "address": "\u200BПроспект Амира Темура, 118/5\u200B2 этаж\nЮнусабадский район, Ташкент, 100099",
        "coordinates": [41.353263, 69.288617],
        "time": "Ежедневно с 11:00 до 02:00"
      },
      "photos": [
        "https://i3.photo.2gis.com/images/branch/0/30258560100423595_b17c_328x170.jpg",
        "https://i4.photo.2gis.com/images/branch/0/30258560100423594_2d21_328x170.jpg"

      ],
      "reviews": [
        {
          "user": "Махамбет Сагаталиев",
          "rating": 5,
          "text": "Playstation \uD83D\uDC4D\uD83C\uDFFB\uD83D\uDC4D\uD83C\uDFFB\uD83D\uDC4D\uD83C\uDFFB. Цена тоже норм"
        }
      ],
      "administration": {
        "contact": "-",
        "number": "+998 (55) 520‒22‒02"
      },
      "services": {
        "Wi-Fi": true,
        "bar":   true,
        "kitchen": true,
        "consoles": true,
        "games": true,
        "relaxation_zones": true
      },
      "prices": {
        "pc_rent_STANDART": 12000,
      "pc_rent_VIP": 14000,
        "special_offers": "Скидка 20% после 22:00"
      },
      "working_hours": "Ежедневно с 11:00 до 02:00",
      "club_card": {
        "loyalty_program": true,
        "benefits": "Скидки постоянным клиентам, бонусные игры"
      },
      "comments": "Дополнительная информация и акции доступны на сайте клуба"
    },
                                            {
      "id": 15,
      "name": "Game Vip Zone",
      "description": "Чем дальше босс от клуба, тем новее мобилы у админов\n\nЧем меньше клуб, тем больше геморроя.",
      "location": {
        "address": "Юнусабад 13-й квартал, 59\u200B1 этаж\u200B2 филиала\nЮнусабад 13-й квартал, Юнусабадский район, Ташкент, 100194",
        "coordinates": [41.305628, 69.301198],
        "time": "Круглосуточно"
      },
      "photos": [
        "https://i4.photo.2gis.com/images/branch/0/30258560111847361_d4d3_328x170.jpg",
        "https://i6.photo.2gis.com/images/branch/0/30258560087757878_d004_328x170.jpg"

      ],
      "reviews": [
        {
          "user": "Асхаб ТАМАЕВ",
          "rating": 5,
          "text": "ПЛОХОЙ КЛУБ И ФОТОГРАФ ЖЕЛЕБ"
        }
      ],
      "administration": {
        "contact": "-",
        "number": "+998 95‒510‒77‒70"
      },
      "services": {
        "Wi-Fi": true,
        "bar":   true,
        "kitchen": true,
        "consoles": true,
        "games": true,
        "relaxation_zones": true
      },
      "prices": {
        "pc_rent_STANDART": 14000,
      "pc_rent_VIP": 18000,
        "special_offers": "Скидка 20% после 22:00"
      },
      "working_hours": "Круглосуточно",
      "club_card": {
        "loyalty_program": true,
        "benefits": "Скидки постоянным клиентам, бонусные игры"
      },
      "comments": "Дополнительная информация и акции доступны на сайте клуба"
    },
    {
    "id": 16,
    "name": "Nexus Gaming Hub",
    "description": "Место, где игровая атмосфера смешивается с современным дизайном. У нас вы найдете все: от уютных зон для отдыха до самых передовых игровых консолей.",
    "location": {
      "address": "улица Мустакиллик, 21, Юнусабадский район, Ташкент, 100060",
      "coordinates": [41.302726, 69.280759],
      "time": "Ежедневно с 10:00 до 02:00"
    },
    "photos": [
      "https://encrypted-tbn0.gstatic.com/images?q=tbn:ANd9GcR8jm8nOxam-OEe-R3_Spzmoh_8wKRGASlmYEjVkszxUspmfVJt86PhQLuysA24Ame1Nqk&usqp=CAU",
      "https://encrypted-tbn0.gstatic.com/images?q=tbn:ANd9GcTTBb7UD4TDOpuRalHEO_ZPPx1J3q1nulB68xW9gaDeeqaGuwaw2Bkf8HSpCJ5UTkG_WI0&usqp=CAU"
    ],
    "reviews": [
      {
        "user": "Иван Петров",
        "rating": 5,
        "text": "Отличное место для проведения времени с друзьями. Всегда чисто и уютно."
      }
    ],
    "administration": {
      "contact": "nexusgaminghub@gmail.com",
      "number": "+998 95‒510‒77‒70"
    },
    "services": {
      "Wi-Fi": true,
      "bar": true,
      "kitchen": true,
      "consoles": true,
      "games": true,
      "relaxation_zones": true
    },
    "prices": {
      "pc_rent_STANDART": 10000,
      "pc_rent_VIP": 20000,
      "special_offers": "Скидка 20% после 22:00"
    },
    "working_hours": "Ежедневно с 10:00 до 02:00",
    "club_card": {
      "loyalty_program": true,
      "benefits": "Скидки постоянным клиентам, бонусные игры"
    },
    "comments": "Дополнительная информация и акции доступны на сайте клуба"
  },
    {
    "id": 17,
    "name": "Galaxy Gaming Arena",
    "description": "Великолепный игровой клуб с атмосферой будущего. Здесь каждый найдет что-то по душе, будь то крутые игры или просто отдых в компании друзей.",
    "location": {
      "address": "улица Мухаммад Юсуфа, 17, Мирабадский район, Ташкент, 100015",
      "coordinates": [41.329394, 69.281478],
      "time": "Круглосуточно"
    },
    "photos": [
      "https://bau-architects.ru/wp-content/uploads/2020/07/CyberSpotLite-gl.jpg",
      "https://encrypted-tbn0.gstatic.com/images?q=tbn:ANd9GcS6aLtdSbe-tiAnC7r7fRgf974bvic9-yjUXVeSyTGxXzwGHrIqBUjA2z73Tbi2Ld1Ifa4&usqp=CAU"
    ],
    "reviews": [
      {
        "user": "Елена Сидорова",
        "rating": 4,
        "text": "Отличное место! Удивительная атмосфера и большой выбор игр. Обязательно приду еще!"
      }
    ],
    "administration": {
      "contact": "galaxygamingarena@gmail.com",
      "number": "+998 71 234-56-78"
    },
    "services": {
      "Wi-Fi": true,
      "bar": true,
      "kitchen": true,
      "consoles": true,
      "games": true,
      "relaxation_zones": true
    },
    "prices": {
      "pc_rent_STANDART": 20000,
      "pc_rent_VIP": 40000,
      "special_offers": "Скидка 15% в будние дни"
    },
    "working_hours": "Круглосуточно",
    "club_card": {
      "loyalty_program": true,
      "benefits": "Бонусы за каждое посещение, скидки на напитки"
    },
    "comments": "Подробности на официальном сайте клуба"
  },
    {
    "id": 18,
    "name": "Virtual Galaxy",
    "description": "Уникальное место для настоящих геймеров. У нас вы найдете самые популярные игры, уютные зоны отдыха и дружелюбную атмосферу.",
    "location": {
      "address": "улица Амира Темура, 42, Яккасарайский район, Ташкент, 100084",
      "coordinates": [41.299482, 69.239184],
      "time": "Ежедневно с 12:00 до 02:00"
    },
    "photos": [
      "https://encrypted-tbn0.gstatic.com/images?q=tbn:ANd9GcTKo0yzqJV8K-WGA49tKT_ZWNJA_2qG2sRUDMWpffz3O7UavMVnwR7nmYtVP8ZMN3hiEGk&usqp=CAU",
      "https://encrypted-tbn0.gstatic.com/images?q=tbn:ANd9GcR00LBe6l9FC3U-F7aV_3pmUQP2c1seTujGMw&usqp=CAU"
    ],
    "reviews": [
      {
        "user": "Алексей Иванов",
        "rating": 5,
        "text": "Отличное место! Всегда приятно проводить время здесь. Рекомендую!"
      }
    ],
    "administration": {
      "contact": "virtualgalaxy@gmail.com",
      "number": "+998 71 987-65-43"
    },
    "services": {
      "Wi-Fi": true,
      "bar": true,
      "kitchen": true,
      "consoles": true,
      "games": true,
      "relaxation_zones": true
    },
    "prices": {
      "pc_rent_STANDART": 20000,
      "pc_rent_VIP": 25000,
      "special_offers": "Скидка 10% при предъявлении студенческого билета"
    },
    "working_hours": "Ежедневно с 12:00 до 02:00",
    "club_card": {
      "loyalty_program": true,
      "benefits": "Скидки для постоянных клиентов, бесплатные напитки"
    },
    "comments": "Более подробная информация доступна на нашем сайте"
  },
    {
    "id": 19,
    "name": "Epic Gamer's Haven",
    "description": "Идеальное место для любителей игр и хорошего отдыха. У нас большой выбор игр, комфортные условия и дружелюбный персонал.",
    "location": {
      "address": "проспект Мустакиллик, 55, Мирзо-Улугбекский район, Ташкент, 100090",
      "coordinates": [41.338746, 69.280983],
      "time": "Пн-Пт: с 14:00 до 02:00, Сб-Вс: круглосуточно"
    },
    "photos": [
      "https://encrypted-tbn0.gstatic.com/images?q=tbn:ANd9GcRcYZlGlTPUYUULOk2ZWeOGvuz5Yb3Tu7FI3A&usqp=CAU",
      "https://encrypted-tbn0.gstatic.com/images?q=tbn:ANd9GcQoJ9B_jqvfQsVNKi4u_ZepF8IrPxORFDaNQg&usqp=CAU"
    ],
    "reviews": [
      {
        "user": "Екатерина Смирнова",
        "rating": 4,
        "text": "Отличное место для проведения времени с друзьями. Понравилась атмосфера и выбор игр."
      }
    ],
    "administration": {
      "contact": "epicgamershaven@gmail.com",
      "number": "+998 71 765-43-21"
    },
    "services": {
      "Wi-Fi": true,
      "bar": true,
      "kitchen": true,
      "consoles": true,
      "games": true,
      "relaxation_zones": true
    },
    "prices": {
      "pc_rent_STANDART": 16000,
      "pc_rent_VIP": 32000,
      "special_offers": "Скидка 15% при бронировании заранее"
    },
    "working_hours": "Пн-Пт: с 14:00 до 02:00, Сб-Вс: круглосуточно",
    "club_card": {
      "loyalty_program": true,
      "benefits": "Бонусы за каждый визит, скидки на бар"
    },
    "comments": "Подробности о наших акциях можно узнать на нашем сайте"
  },
      {
    "id": 20,
    "name": "Cyber Zone",
    "description": "Игровой клуб для настоящих ценителей виртуального мира. У нас широкий выбор игр, отличная атмосфера и дружелюбный персонал.",
    "location": {
      "address": "улица Фурката, 18, Ташкент, Чиланзарский район, 100124",
      "coordinates": [41.316672, 69.241318],
      "time": "Круглосуточно"
    },
    "photos": [
      "https://encrypted-tbn0.gstatic.com/images?q=tbn:ANd9GcRzenyuKU3VrEOd-u2XPKFqCyIQjxChTYA9Vg&usqp=CAU",
      "https://encrypted-tbn0.gstatic.com/images?q=tbn:ANd9GcQY897JjUufSZ3OE-fy02Q93B2JrrSTJ9enQA&usqp=CAU"
    ],
    "reviews": [
      {
        "user": "Максим Соколов",
        "rating": 4,
        "text": "Отличное место для игр! Уютная атмосфера и большой выбор игровых платформ."
      }
    ],
    "administration": {
      "contact": "cyberzonetashkent@gmail.com",
      "number": "+998 71 543-21-09"
    },
    "services": {
      "Wi-Fi": true,
      "bar": true,
      "kitchen": true,
      "consoles": true,
      "games": true,
      "relaxation_zones": true
    },
    "prices": {
      "pc_rent_STANDART": 15000,
      "pc_rent_VIP": 20000,
      "special_offers": "Скидка 10% для студентов"
    },
    "working_hours": "Круглосуточно",
    "club_card": {
      "loyalty_program": true,
      "benefits": "Бонусы за посещения и скидки на напитки"
    },
    "comments": "Дополнительную информацию можно получить на нашем официальном сайте"
  },
          {
    "id": 21,
    "name": "Traffic",
    "description": "Интернет-кафе киберспорт игровой клуб",
    "location": {
      "address": "\nЧиланзарский район, массив Чиланзор, 18-й квартал, 9",
      "coordinates": [41.272504, 69.191554],
      "time": "Круглосуточно"
    },
    "photos": [
      "https://avatars.mds.yandex.net/get-altay/4538345/2a0000017825d2667297fd3cd99cee054aeb/XXXL",
      "https://avatars.mds.yandex.net/get-altay/4280929/2a000001783f46ae9d03aaa09509d478d21d/XXXL"
    ],
    "reviews": [
      {
        "user": "Шадияр Абилкасимов",
        "rating": 5,
        "text": "Отличное место, уютно и удобно. Админы всегда помогут и система кондиционирования работает на ура"
      }
    ],
    "administration": {
      "contact": "cyberzonetashkent@gmail.com",
      "number": "+\n+998 95 515 11 00"
    },
    "services": {
      "Wi-Fi": true,
      "bar": true,
      "kitchen": true,
      "consoles": true,
      "games": true,
      "relaxation_zones": true
    },
    "prices": {
      "pc_rent_STANDART": 15000,
      "pc_rent_VIP": 22000,
      "special_offers": "Скидка 10% для студентов"
    },
    "working_hours": "Круглосуточно",
    "club_card": {
      "loyalty_program": true,
      "benefits": "Бонусы за посещения и скидки на напитки"
    },
    "comments": "Дополнительную информацию можно получить на нашем официальном сайте"
  },
              {
    "id": 22,
    "name": "Tokyo. PC",
    "description": "Интернет-кафе",
    "location": {
      "address": "Ташкент, ул. Олой Бозори, 23 этаж 2",
      "coordinates": [41.318257, 69.286704],
      "time": "Круглосуточно"
    },
    "photos": [
      "https://avatars.mds.yandex.net/get-altay/918124/2a000001617a78d31cbbb4ae7ee9a4e2779c/XXXL",
      "https://avatars.mds.yandex.net/get-altay/910613/2a0000018c6450d34e7f49c6def76ba459fb/XXXL"
    ],
    "reviews": [
      {
        "user": "\nLaziza Pulatova",
        "rating": 5,
        "text": "Раз в год я приглашаю значимых друзей в это место только ради донеров. Донеры здесь — произведение искусства. Я, как жительница Узбекистана, привыкла к тому, что еда почти везде всегда вкусная. Для меня, когда «очень вкусно» это просто база, но донеры здесь это высший пилотаж. Это вальс Доги, это Ранэвэй Канье Уэста, это Ne boldi Севинч Муминовой, это «Впечатление» Клода Моне, это Ренессанс, это весна моего сердца. Когда я окажусь перед Аллахом и он спросит, жила ли я, я отвечу да и приведу в этом место. Бесконечный респект и баракат всем поварам и всему персоналу. Любовь"
      }
    ],
    "administration": {
      "contact": "cyberzonetashkent@gmail.com",
      "number": "+\n+998 95 515 11 00"
    },
    "services": {
      "Wi-Fi": true,
      "bar": true,
      "kitchen": true,
      "consoles": true,
      "games": true,
      "relaxation_zones": true
    },
    "prices": {
      "pc_rent_STANDART": 12000,
      "pc_rent_VIP": 20000,
      "special_offers": "Скидка 10% для студентов"
    },
    "working_hours": "Круглосуточно",
    "club_card": {
      "loyalty_program": true,
      "benefits": "Бонусы за посещения и скидки на напитки"
    },
    "comments": "Дополнительную информацию можно получить на нашем официальном сайте"
  },
                  {
    "id": 23,
    "name": "Cyberium.uz",
    "description": "Интернет-кафе киберспорт развлекательный центр",
    "location": {
      "address": "Ташкент, ул. Мирабад, 2/1",
      "coordinates": [41.318257, 69.286704],
      "time": "Круглосуточно"
    },
    "photos": [
      "https://avatars.mds.yandex.net/get-altay/918124/2a000001617a78d31cbbb4ae7ee9a4e2779c/XXXL",
      "https://avatars.mds.yandex.net/get-altay/910613/2a0000018c6450d34e7f49c6def76ba459fb/XXXL"
    ],
    "reviews": [
      {
        "user": "\nLaziza Pulatova",
        "rating": 5,
        "text": "Раз в год я приглашаю значимых друзей в это место только ради донеров. Донеры здесь — произведение искусства. Я, как жительница Узбекистана, привыкла к тому, что еда почти везде всегда вкусная. Для меня, когда «очень вкусно» это просто база, но донеры здесь это высший пилотаж. Это вальс Доги, это Ранэвэй Канье Уэста, это Ne boldi Севинч Муминовой, это «Впечатление» Клода Моне, это Ренессанс, это весна моего сердца. Когда я окажусь перед Аллахом и он спросит, жила ли я, я отвечу да и приведу в этом место. Бесконечный респект и баракат всем поварам и всему персоналу. Любовь"
      }
    ],
    "administration": {
      "contact": "TokyoPCtashkent@gmail.com",
      "number": "+\n+998 95 515 11 00"
    },
    "services": {
      "Wi-Fi": true,
      "bar": true,
      "kitchen": true,
      "consoles": true,
      "games": true,
      "relaxation_zones": true
    },
    "prices": {
      "pc_rent_STANDART": 20000,
      "pc_rent_VIP": 50000,
      "special_offers": "Скидка 10% для студентов"
    },
    "working_hours": "Круглосуточно",
    "club_card": {
      "loyalty_program": true,
      "benefits": "Бонусы за посещения и скидки на напитки"
    },
    "comments": "Дополнительную информацию можно получить на нашем официальном сайте"
  },
                      {
    "id": 24,
    "name": "Fidanza",
    "description": "Интернет-кафе киберспорт развлекательный центр",
    "location": {
      "address": "Ташкент, Юнусабадский район, махалля Севинч, улица Юнусата 14\n",
      "coordinates": [41.370929, 69.310413],
      "time": "Круглосуточно"
    },
    "photos": [
      "https://encrypted-tbn0.gstatic.com/images?q=tbn:ANd9GcQ0USKBs7g2H8bi43r-AMsG1g3aCvLK8WZaxA&usqp=CAU",
      "https://avatars.mds.yandex.net/get-altay/1881714/2a0000018637b42467f5d9f916ce3f31ad71/orig"
    ],
    "reviews": [
      {
        "user": "Умарбек Муроджонов",
        "rating": 5,
        "text": "Один из лучших игровых клубов по моему мнение, особенно кайфово отдельные кабинки 5х5 для любителей контр-страйка доты и тд, для игры команда на команду, весь шум гам остается там, цены лучшие в городе, персонал приветливые, остался доволен после похода туда"
      }
    ],
    "administration": {
      "contact": "fidanzatashkent@gmail.com",
      "number": "+998 95 144 24 42"
    },
    "services": {
      "Wi-Fi": true,
      "bar": true,
      "kitchen": true,
      "consoles": true,
      "games": true,
      "relaxation_zones": true
    },
    "prices": {
      "pc_rent_STANDART": 12000,
      "pc_rent_VIP": 15000,
      "special_offers": "Скидка 10% для студентов"
    },
    "working_hours": "Круглосуточно",
    "club_card": {
      "loyalty_program": true,
      "benefits": "Бонусы за посещения и скидки на напитки"
    },
    "comments": "Дополнительную информацию можно получить на нашем официальном сайте"
  },
                          {
    "id": 25,
    "name": "Fidanza",
    "description": "Интернет-кафе киберспорт развлекательный центр",
    "location": {
      "address": "Ташкент, Юнусабадский район, махалля Севинч, улица Юнусата 14\n",
      "coordinates": [41.370929, 69.310413],
      "time": "Круглосуточно"
    },
    "photos": [
      "https://encrypted-tbn0.gstatic.com/images?q=tbn:ANd9GcQ0USKBs7g2H8bi43r-AMsG1g3aCvLK8WZaxA&usqp=CAU",
      "https://avatars.mds.yandex.net/get-altay/1881714/2a0000018637b42467f5d9f916ce3f31ad71/orig"
    ],
    "reviews": [
      {
        "user": "Умарбек Муроджонов",
        "rating": 5,
        "text": "Один из лучших игровых клубов по моему мнение, особенно кайфово отдельные кабинки 5х5 для любителей контр-страйка доты и тд, для игры команда на команду, весь шум гам остается там, цены лучшие в городе, персонал приветливые, остался доволен после похода туда"
      }
    ],
    "administration": {
      "contact": "fidanzatashkent@gmail.com",
      "number": "+998 95 144 24 42"
    },
    "services": {
      "Wi-Fi": true,
      "bar": true,
      "kitchen": true,
      "consoles": true,
      "games": true,
      "relaxation_zones": true
    },
    "prices": {
      "pc_rent_STANDART": 14000,
      "pc_rent_VIP": 16500,
      "special_offers": "Скидка 10% для студентов"
    },
    "working_hours": "Круглосуточно",
    "club_card": {
      "loyalty_program": true,
      "benefits": "Бонусы за посещения и скидки на напитки"
    },
    "comments": "Дополнительную информацию можно получить на нашем официальном сайте"
  },
                              {
    "id": 26,
    "name": "Lvl Up",
    "description": "\nИнтернет-кафе",
    "location": {
      "address": "Ташкент, Шайхантахурский район, массив Хадра, 23",
      "coordinates": [41.327107, 69.249338],
      "time": "Круглосуточно"
    },
    "photos": [
      "https://encrypted-tbn0.gstatic.com/images?q=tbn:ANd9GcQ0USKBs7g2H8bi43r-AMsG1g3aCvLK8WZaxA&usqp=CAU",
      "https://avatars.mds.yandex.net/get-altay/1881714/2a0000018637b42467f5d9f916ce3f31ad71/orig"
    ],
    "reviews": [
      {
        "user": "Санжар Ахмедов",
        "rating": 5,
        "text": "Классный клуб,как для онлайн та и для офлайн игр, отличный админы которые знают свою работу,чутка какие-то вопросы сразу реагируют,и компы без лагов, отдыхаем часто,довольны на все 100%"
      }
    ],
    "administration": {
      "contact": "LVLtashkent@gmail.com",
      "number": "+998 95 144 24 42"
    },
    "services": {
      "Wi-Fi": true,
      "bar": true,
      "kitchen": true,
      "consoles": true,
      "games": true,
      "relaxation_zones": true
    },
    "prices": {
      "pc_rent_STANDART": 10000,
      "pc_rent_VIP": 13000,
      "special_offers": "Скидка 10% для студентов"
    },
    "working_hours": "Круглосуточно",
    "club_card": {
      "loyalty_program": true,
      "benefits": "Бонусы за посещения и скидки на напитки"
    },
    "comments": "Дополнительную информацию можно получить на нашем официальном сайте"
  },
                                  {
    "id": 27,
    "name": "Adrenalinet",
    "description": "Интернет-кафе",
    "location": {
      "address": "\nул. Шота Руставели, 53",
      "coordinates": [41.285504, 69.254316],
      "time": "Круглосуточно"
    },
    "photos": [
      "https://encrypted-tbn0.gstatic.com/images?q=tbn:ANd9GcQ2XOI0lZO1CmFB7Xj38J84Z98i8Kt7J9t4Eg&usqp=CAU",
      "https://encrypted-tbn0.gstatic.com/images?q=tbn:ANd9GcRs8-945d9G7xztBh-0pDb0WsoQrKgRpolRVq58Jx3_lLNFNMKtOvqJ50VuwE6di0izxYM&usqp=CAU"
    ],
    "reviews": [
      {
        "user": "Rafael Rustamovich",
        "rating": 5,
        "text": "Наверное это лучший клуб в городе! Наличие кабинок с PS это плюс, а кабинка кинотеатр, в которой можно посмотреть фильмы, поиграть в PS или в настольные игры с большой компанией, это вообще супер!"
      }
    ],
    "administration": {
      "contact": "Adrenalinettashkent@gmail.com",
      "number": "+998 95 144 24 42"
    },
    "services": {
      "Wi-Fi": true,
      "bar": true,
      "kitchen": true,
      "consoles": true,
      "games": true,
      "relaxation_zones": true
    },
    "prices": {
      "pc_rent_STANDART": 16000,
      "pc_rent_VIP": 18000,
      "special_offers": "Скидка 10% для студентов"
    },
    "working_hours": "Круглосуточно",
    "club_card": {
      "loyalty_program": true,
      "benefits": "Бонусы за посещения и скидки на напитки"
    },
    "comments": "Дополнительную информацию можно получить на нашем официальном сайте"
  },
                                      {
    "id": 28,
    "name": "B2_game",
    "description": "Интернет-кафе",
    "location": {
      "address": "\nул. Шахрисабз, 1Б этаж -1",
      "coordinates": [41.309505, 69.287184],
      "time": "Круглосуточно"
    },
    "photos": [
      "https://encrypted-tbn0.gstatic.com/images?q=tbn:ANd9GcQ2XOI0lZO1CmFB7Xj38J84Z98i8Kt7J9t4Eg&usqp=CAU",
      "https://encrypted-tbn0.gstatic.com/images?q=tbn:ANd9GcRs8-945d9G7xztBh-0pDb0WsoQrKgRpolRVq58Jx3_lLNFNMKtOvqJ50VuwE6di0izxYM&usqp=CAU"
    ],
    "reviews": [
      {
        "user": "Рамазан Палванов",
        "rating": 5,
        "text": "приветливые сотрудники и можно поводить машину как в реальной жизни"
      }
    ],
    "administration": {
      "contact": "B2tashkent@gmail.com",
      "number": "\n+998 881 97 57 77"
    },
    "services": {
      "Wi-Fi": true,
      "bar": true,
      "kitchen": true,
      "consoles": true,
      "games": true,
      "relaxation_zones": true
    },
    "prices": {
      "pc_rent_STANDART": 13000,
      "pc_rent_VIP": 15000,
      "special_offers": "Скидка 40% для инвалидов"
    },
    "working_hours": "Круглосуточно",
    "club_card": {
      "loyalty_program": true,
      "benefits": "Бонусы за посещения и скидки на напитки"
    },
    "comments": "Дополнительную информацию можно получить на нашем официальном сайте"
  },
                                          {
    "id": 29,
    "name": "Imperial",
    "description": "Интернет-кафе",
    "location": {
      "address": "Яшнободский район, массив Тузель, 2-й квартал, 15В",
      "coordinates": [41.290037, 69.359923],
      "time": "Круглосуточно"
    },
    "photos": [
      "https://avatars.mds.yandex.net/get-altay/1881714/2a0000018637b42467f5d9f916ce3f31ad71/XXXL",
      "https://avatars.mds.yandex.net/get-altay/4388821/2a000001794b01418301bab93461eb3e92fd/XXXL"
    ],
    "reviews": [
      {
        "user": "\nВячеслв Цхэ",
        "rating": 5,
        "text": "Думаю самый играбельный клуб района.\nДействительно дружеская, уютная атмосфера. Порядок и чистота на уровне. Игровой клуб для своих)\nПорядочные и отзывчивые администратор вры."
      }
    ],
    "administration": {
      "contact": "IMPERIALtashkent@gmail.com",
      "number": "+998 90 944-11-42"
    },
    "services": {
      "Wi-Fi": true,
      "bar": true,
      "kitchen": true,
      "consoles": true,
      "games": true,
      "relaxation_zones": true
    },
    "prices": {
      "pc_rent_STANDART": 13000,
      "pc_rent_VIP": 15000,
      "special_offers": "Скидка постоянным клиентам"
    },
    "working_hours": "Круглосуточно",
    "club_card": {
      "loyalty_program": true,
      "benefits": "Бонусы за посещения и скидки на напитки"
    },
    "comments": "Дополнительную информацию можно получить на нашем официальном сайте"
  },
    {
    "id": 30,
    "name": "Fox gaming",
    "description": "Интернет-кафе компьютерный клуб игровой клуб",
    "location": {
      "address": "Яшнободский район, тупик Мавляна Риёзи, 31 этаж -1",
      "coordinates": [41.314098, 69.325389],
      "time": "Круглосуточно"
    },
    "photos": [
      "https://avatars.mds.yandex.net/get-altay/7379963/2a000001868e3348f29ad6644eb5e67acda3/XXXL",
      "https://avatars.mds.yandex.net/get-altay/953593/2a000001868e332f66a48b0ad6485dad1e82/XXXL"
    ],
    "reviews": [
      {
        "user": "БУБСИК",
        "rating": 5,
        "text": "Думаю самый играбельный клуб района.\nДействительно дружеская, уютная атмосфера. Порядок и чистота на уровне. Игровой клуб для своих)\nПорядочные и отзывчивые администратор вры."
      }
    ],
    "administration": {
      "contact": "FOXGAME@gmail.com",
      "number": "+998 90 037 19 05"
    },
    "services": {
      "Wi-Fi": true,
      "bar": true,
      "kitchen": true,
      "consoles": true,
      "games": true,
      "relaxation_zones": true
    },
    "prices": {
      "pc_rent_STANDART": 13000,
      "pc_rent_VIP": 15000,
      "special_offers": "Скидка постоянным клиентам"
    },
    "working_hours": "Круглосуточно",
    "club_card": {
      "loyalty_program": true,
      "benefits": "Бонусы за посещения и скидки на напитки"
    },
    "comments": "Дополнительную информацию можно получить на нашем официальном сайте"
  },
      {
    "id": 31,
    "name": "XXxGAMING",
    "description": "Интернет-кафе компьютерный клуб игровой клуб",
    "location": {
      "address": "\nул. Гейдара Алиева, 204",
      "coordinates": [41.314098, 69.325389],
      "time": "Круглосуточно"
    },
    "photos": [
      "https://avatars.mds.yandex.net/get-altay/3798254/2a00000176d305335b0b33df6eb960d7bcdf/XXXL",
      "https://avatars.mds.yandex.net/get-altay/4614377/2a0000017772190dfd0c31e4314d5f00fc33/XXXL"
    ],
    "reviews": [
      {
        "user": "Журабек Бахронов",
        "rating": 4,
        "text": "Хорошая локация,приветливые сотрудники,электроника качественная но не для полного удовольствия"
      }
    ],
    "administration": {
      "contact": "XXxGAMING@gmail.com",
      "number": "+998 95 500 00 77"
    },
    "services": {
      "Wi-Fi": true,
      "bar": true,
      "kitchen": true,
      "consoles": true,
      "games": true,
      "relaxation_zones": true
    },
    "prices": {
      "pc_rent_STANDART": 11000,
      "pc_rent_VIP": 17000,
      "special_offers": "Скидка постоянным клиентам"
    },
    "working_hours": "Круглосуточно",
    "club_card": {
      "loyalty_program": true,
      "benefits": "Бонусы за посещения и скидки на напитки"
    },
    "comments": "Дополнительную информацию можно получить на нашем официальном сайте"
  },
      {
    "id": 32,
    "name": "Headshot Game Club",
    "description": "Интернет-кафе компьютерный клуб игровой клуб",
    "location": {
      "address": "\nул. Тахтагуль, 32Аэтаж 1",
      "coordinates": [41.286029, 69.196004],
      "time": "Круглосуточно"
    },
    "photos": [
      "https://encrypted-tbn0.gstatic.com/images?q=tbn:ANd9GcSm8SCf-NZriIOygyHKRyiGtjtlY0qJt5Rx2A&usqp=CAU",
      "https://encrypted-tbn0.gstatic.com/images?q=tbn:ANd9GcSCH784IrsrklspXBb_x3bPFX70EVVLXmNHTA&usqp=CAU"
    ],
    "reviews": [
      {
        "user": "Журабек Бахронов",
        "rating": 4,
        "text": "Хорошая локация,приветливые сотрудники,электроника качественная но не для полного удовольствия"
      }
    ],
    "administration": {
      "contact": "HeadshotGameClub@gmail.com",
      "number": "+998 93 894 08 12"
    },
    "services": {
      "Wi-Fi": true,
      "bar": true,
      "kitchen": true,
      "consoles": true,
      "games": true,
      "relaxation_zones": true
    },
    "prices": {
      "pc_rent_STANDART": 12000,
      "pc_rent_VIP": 30000,
      "special_offers": "Скидка постоянным клиентам"
    },
    "working_hours": "Круглосуточно",
    "club_card": {
      "loyalty_program": true,
      "benefits": "Бонусы за посещения и скидки на напитки"
    },
    "comments": "Дополнительную информацию можно получить на нашем официальном сайте"
  },
          {
    "id": 33,
    "name": "Феникс",
    "description": "Интернет-кафе игровые приставки игровой клуб",
    "location": {
      "address": "\nобводная ул. Нурафшон, 79",
      "coordinates": [41.335411, 69.221448],
      "time": "Круглосуточно"
    },
    "photos": [
      "https://avatars.mds.yandex.net/get-altay/5457654/2a0000017e8c65ce65377eaa2d6f0cfb5af3/XXXL",
      "https://avatars.mds.yandex.net/get-altay/5457654/2a0000017e8c65ce65377eaa2d6f0cfb5af3/XXXL"
    ],
    "reviews": [
      {
        "user": "Коробчук Артем",
        "rating": 5,
        "text": "ТОП МЕСТО!!!"
      }
    ],
    "administration": {
      "contact": "HeadshotGameClub@gmail.com",
      "number": "+998 93 894 08 12"
    },
    "services": {
      "Wi-Fi": true,
      "bar": true,
      "kitchen": true,
      "consoles": true,
      "games": true,
      "relaxation_zones": true
    },
    "prices": {
      "pc_rent_STANDART": 15000,
      "pc_rent_VIP": 25000,
      "special_offers": "Скидка постоянным клиентам"
    },
    "working_hours": "Круглосуточно",
    "club_card": {
      "loyalty_program": true,
      "benefits": "Бонусы за посещения и скидки на напитки"
    },
    "comments": "Дополнительную информацию можно получить на нашем официальном сайте"
  },
              {
    "id": 34,
    "name": "AG-PASHALKA",
    "description": "Интернет-кафе игровые приставки игровой клуб",
    "location": {
      "address": "УЛИЦА ЗАЕБЦОВА-ДОМ СТРЕЛЬЦОВА 13",
      "coordinates": [41.259862, 69.255352],
      "time": "Круглосуточно"
    },
    "photos": [
      "https://i.ibb.co/JHTCWYn/photo-2024-02-22-02-45-51.jpg",
      "https://i.ibb.co/3vXwv2d/photo-2024-02-22-02-45-41.jpg"
    ],
    "reviews": [
      {
        "user": "Коробчук Артем",
        "rating": 5,
        "text": "ТОП МЕСТО!!!"
      }
    ],
    "administration": {
      "contact": "Bomin@gmail.com",
      "number": "+998 93 894 08 12"
    },
    "services": {
      "Wi-Fi": true,
      "bar": true,
      "kitchen": true,
      "consoles": true,
      "games": true,
      "relaxation_zones": true
    },
    "prices": {
      "pc_rent_STANDART": 0,
      "pc_rent_VIP": 1,
      "special_offers": "Скидка постоянным клиентам"
    },
    "working_hours": "Круглосуточно",
    "club_card": {
      "loyalty_program": true,
      "benefits": "Бонусы за посещения и скидки на напитки"
    },
    "comments": "Дополнительную информацию можно получить на нашем официальном сайте"
  },
          {
    "id": 35,
    "name": "Cougar Game Club",
    "description": "Игровой клуб интернет-кафе",
    "location": {
      "address": "\nТашкент, Сергелийский район, махалля Янги-Сергели 1",
      "coordinates": [41.221088, 69.218441],
      "time": "Круглосуточно"
    },
    "photos": [
      "https://avatars.mds.yandex.net/get-altay/4449685/2a000001828d910110ba6f0e34250c12b0cf/XXXL",
      "https://avatars.mds.yandex.net/get-altay/11396712/2a0000018d23bfafbca43a939fd0f8affcbf/XXXL"
    ],
    "reviews": [
      {
        "user": "Akbar Gafurov",
        "rating": 4,
        "text": "Самые напряженные ночи в играх проводятся здесь. Также хорошее место, чтобы заняться дизайном, попробуйте прийти позже вечером, так как обычно здесь может быть слишком людно (смотрите это как отличное портфолио с описанием)."
      }
    ],
    "administration": {
      "contact": "COUGAR@gmail.com",
      "number": "+998 93 894 08 12"
    },
    "services": {
      "Wi-Fi": true,
      "bar": true,
      "kitchen": true,
      "consoles": true,
      "games": true,
      "relaxation_zones": true
    },
    "prices": {
      "pc_rent_STANDART": 13000,
      "pc_rent_VIP": 16000,
      "special_offers": "Скидка постоянным клиентам"
    },
    "working_hours": "Круглосуточно",
    "club_card": {
      "loyalty_program": true,
      "benefits": "Бонусы за посещения и скидки на напитки"
    },
    "comments": "Дополнительную информацию можно получить на нашем официальном сайте"
  },
              {
    "id": 36,
    "name": "Pantera Club",
    "description": "Игровой клуб интернет-кафе",
    "location": {
      "address": "Tашкент, Сергелийский район, массив Курувчи, 3А",
      "coordinates": [41.217975, 69.259948],
      "time": "Круглосуточно"
    },
    "photos": [
      "https://encrypted-tbn0.gstatic.com/images?q=tbn:ANd9GcT0u2sxnA5vUncqedvNIsBS_053I7oxNkuA4Q&usqp=CAU",
      "https://encrypted-tbn0.gstatic.com/images?q=tbn:ANd9GcRwjkg7pnaR-6m-P00unbiWBpW10jt4cjbSzQ&usqp=CAU"
    ],
    "reviews": [
      {
        "user": "Akbar Gafurov",
        "rating": 5,
        "text": "Самые напряженные ночи в играх проводятся здесь. Также хорошее место, чтобы заняться дизайном, попробуйте прийти позже вечером, так как обычно здесь может быть слишком людно (смотрите это как отличное портфолио с описанием)."
      }
    ],
    "administration": {
      "contact": "PanteraClub@gmail.com",
      "number": "+998 93 894 08 12"
    },
    "services": {
      "Wi-Fi": true,
      "bar": true,
      "kitchen": true,
      "consoles": true,
      "games": true,
      "relaxation_zones": true
    },
    "prices": {
      "pc_rent_STANDART": 13000,
      "pc_rent_VIP": 16000,
      "special_offers": "Скидка постоянным клиентам"
    },
    "working_hours": "8.00-22.00",
    "club_card": {
      "loyalty_program": true,
      "benefits": "Бонусы за посещения и скидки на напитки"
    },
    "comments": "Дополнительную информацию можно получить на нашем официальном сайте"
  },
                  {
    "id": 37,
    "name": "Toman",
    "description": "Игровой клуб интернет-кафе",
    "location": {
      "address": "Ташкент, Мирабадский район, махалля Зиёнур",
      "coordinates": [41.249677, 69.302627],
      "time": "Круглосуточно"
    },
    "photos": [
      "https://encrypted-tbn0.gstatic.com/images?q=tbn:ANd9GcSD6pV7CoANZW5iu1htUMh5VaO9DuQ5d0hFCA&usqp=CAU",
      "https://encrypted-tbn0.gstatic.com/images?q=tbn:ANd9GcQW999AZleOV962I54Kv7owAr3q-Msk2v-OmQ&usqp=CAU"
    ],
    "reviews": [
      {
        "user": "Usmonov Usmonxon",
        "rating": 5,
        "text": "Хороший места."
      }
    ],
    "administration": {
      "contact": "TomanClub@gmail.com",
      "number": "+998 93 894 08 12"
    },
    "services": {
      "Wi-Fi": true,
      "bar": true,
      "kitchen": true,
      "consoles": true,
      "games": true,
      "relaxation_zones": true
    },
    "prices": {
      "pc_rent_STANDART": 13000,
      "pc_rent_VIP": 16000,
      "special_offers": "Скидка постоянным клиентам"
    },
    "working_hours": "Круглосуточно",
    "club_card": {
      "loyalty_program": true,
      "benefits": "Бонусы за посещения и скидки на напитки"
    },
    "comments": "Дополнительную информацию можно получить на нашем официальном сайте"
  },
                      {
    "id": 38,
    "name": "Fidanza",
    "description": "Игровой клуб интернет-кафе",
    "location": {
      "address": "\nЯшнободский район, массив Городок Авиастроителей, 2-й квартал, 40",
      "coordinates": [41.284383, 69.343586],
      "time": "Круглосуточно"
    },
    "photos": [
      "https://encrypted-tbn0.gstatic.com/images?q=tbn:ANd9GcR42ht5ceU2y_FhJKkjUC02t-EP33SDCWMuUA&usqp=CAU",
      "https://encrypted-tbn0.gstatic.com/images?q=tbn:ANd9GcT722LGOLBZz2pwUr32Jk6jexqABunrg0AZtw&usqp=CAU"
    ],
    "reviews": [
      {
        "user": "БУХАЛО",
        "rating": 3,
        "text": "Ну среднячок"
      }
    ],
    "administration": {
      "contact": "FidanzaClub@gmail.com",
      "number": "+998 71 294 07 70"
    },
    "services": {
      "Wi-Fi": true,
      "bar": true,
      "kitchen": true,
      "consoles": true,
      "games": true,
      "relaxation_zones": true
    },
    "prices": {
      "pc_rent_STANDART": 9000,
      "pc_rent_VIP": 12000,
      "special_offers": "Скидка постоянным клиентам"
    },
    "working_hours": "Круглосуточно",
    "club_card": {
      "loyalty_program": true,
      "benefits": "Бонусы за посещения и скидки на напитки"
    },
    "comments": "Дополнительную информацию можно получить на нашем официальном сайте"
  },
                          {
    "id": 39,
    "name": "Internet",
    "description": "Игровой клуб интернет-кафе",
    "location": {
      "address": "\nТашкент, Чиланзарский район, массив Аль-Хорезми-2, 56",
      "coordinates": [41.263638, 69.161490],
      "time": "Круглосуточно"
    },
    "photos": [
      "https://encrypted-tbn0.gstatic.com/images?q=tbn:ANd9GcTk_1M22lBa8SLAMJg1-N8Pw7ivSrv7-oJClw&usqp=CAU",
      "https://encrypted-tbn0.gstatic.com/images?q=tbn:ANd9GcQecHpPER5AClrE9gHOq7gH7GzVtlnSgzj0YoOfJwpzskUTRQNU_pTrA2ovcYxPxuJC-gY&usqp=CAU"
    ],
    "reviews": [
      {
        "user": "Usmonov Usmonxon",
        "rating": 3,
        "text": "Ну среднячок"
      }
    ],
    "administration": {
      "contact": "InternetClub@gmail.com",
      "number": "+998 93 894 08 12"
    },
    "services": {
      "Wi-Fi": true,
      "bar": true,
      "kitchen": true,
      "consoles": true,
      "games": true,
      "relaxation_zones": true
    },
    "prices": {
      "pc_rent_STANDART": 10000,
      "pc_rent_VIP": 12000,
      "special_offers": "Скидка постоянным клиентам"
    },
    "working_hours": "Круглосуточно",
    "club_card": {
      "loyalty_program": true,
      "benefits": "Бонусы за посещения и скидки на напитки"
    },
    "comments": "Дополнительную информацию можно получить на нашем официальном сайте"
  },
                              {
    "id": 40,
    "name": "Gravity",
    "description": "Игровой клуб интернет-кафе",
    "location": {
      "address": "\n1-й пр. Авиасозлар, 22",
      "coordinates": [41.292871, 69.334961],
      "time": "Круглосуточно"
    },
    "photos": [
      "https://avatars.mds.yandex.net/get-altay/4530524/2a000001772d3d7e9d59f1295c4c9be09ca9/XXXL",
      "https://encrypted-tbn0.gstatic.com/images?q=tbn:ANd9GcQKC3q9W-ewJGNxKp9U5OE6clGvFbDUsbzdTg&usqp=CAU"
    ],
    "reviews": [
      {
        "user": "ЕРБОЛА АЗИМА",
        "rating": 2,
        "text": "Воняет там не советую ходить"
      }
    ],
    "administration": {
      "contact": "Gravity@gmail.com",
      "number": "\n+998 90 968 91 61"
    },
    "services": {
      "Wi-Fi": true,
      "bar": true,
      "kitchen": true,
      "consoles": true,
      "games": true,
      "relaxation_zones": true
    },
    "prices": {
      "pc_rent_STANDART": 12000,
      "pc_rent_VIP": 14000,
      "special_offers": "Скидка постоянным клиентам"
    },
    "working_hours": "Круглосуточно",
    "club_card": {
      "loyalty_program": true,
      "benefits": "Бонусы за посещения и скидки на напитки"
    },
    "comments": "Дополнительную информацию можно получить на нашем официальном сайте"
  }
  ]
}